napari_proofread_brainbow/__init__.py
napari_proofread_brainbow/_version.py
napari_proofread_brainbow/_widget.py
napari_proofread_brainbow/napari.yaml
napari_proofread_brainbow/_tests/__init__.py
napari_proofread_brainbow/_tests/test_widget.py
napari_proofread_brainbow-0.3.1.dist-info/licenses/LICENSE
napari_proofread_brainbow-0.3.1.dist-info/METADATA
napari_proofread_brainbow-0.3.1.dist-info/WHEEL
napari_proofread_brainbow-0.3.1.dist-info/entry_points.txt
napari_proofread_brainbow-0.3.1.dist-info/top_level.txt
napari_proofread_brainbow-0.3.1.dist-info/RECORD
